_getargv.cpython-314-darwin.so
getargv/__init__.py
getargv/__init__.pyi
getargv/_getargv.pyi
getargv/_getargvmodule.c
getargv/py.typed
getargv-0.20.dist-info/licenses/LICENSE.txt
getargv-0.20.dist-info/METADATA
getargv-0.20.dist-info/WHEEL
getargv-0.20.dist-info/top_level.txt
getargv-0.20.dist-info/RECORD
