Metadata-Version: 2.4
Name: getargv
Version: 0.20
Summary: Python bindings to libgetargv, a library to correctly and quickly get other process's args
Home-page: https://getargv.narzt.cam
Author: Camden Narzt
Author-email: Camden Narzt <getargv@narzt.cam>
Project-URL: Repository, https://github.com/getargv/getargv.py
Project-URL: Issues, https://github.com/getargv/getargv.py/issues
Project-URL: Homepage, https://getargv.narzt.cam
Project-URL: Documentation, https://getargv.github.io/getargv.py
Project-URL: Funding, https://github.com/sponsors/CamJN
Classifier: Development Status :: 3 - Alpha
Classifier: Environment :: Console
Classifier: Environment :: MacOS X
Classifier: Intended Audience :: Developers
Classifier: Intended Audience :: Information Technology
Classifier: Intended Audience :: System Administrators
Classifier: Operating System :: MacOS :: MacOS X
Classifier: Programming Language :: Python
Classifier: Programming Language :: C
Classifier: Programming Language :: Python :: Implementation :: CPython
Requires-Python: >=3.9
License-File: LICENSE.txt
Dynamic: author
Dynamic: home-page
Dynamic: license-file
